{
  "animation.css": "animation-971ed69949.css",
  "pingouManager/createPingou.css": "pingouManager/createPingou-430d51f5a8.css",
  "pingouManager/dialog.css": "pingouManager/dialog-074bfd44fb.css",
  "pingouManager/form.css": "pingouManager/form-13f5d8679a.css",
  "rev/animation-971ed69949.css": "rev/animation-971ed69949-971ed69949.css",
  "rev/pingouManager/createPingou-430d51f5a8.css": "rev/pingouManager/createPingou-430d51f5a8-430d51f5a8.css",
  "rev/pingouManager/dialog-074bfd44fb.css": "rev/pingouManager/dialog-074bfd44fb-074bfd44fb.css",
  "rev/pingouManager/form-13f5d8679a.css": "rev/pingouManager/form-13f5d8679a-13f5d8679a.css",
  "rev/test-466b570c16.css": "rev/test-466b570c16-466b570c16.css",
  "rev/test2-f13f9c6134.css": "rev/test2-f13f9c6134-f13f9c6134.css",
  "rev/test3-112b026e30.css": "rev/test3-112b026e30-112b026e30.css",
  "rev/test4-c1beb93e56.css": "rev/test4-c1beb93e56-c1beb93e56.css",
  "rev/test5-9d58c636cc.css": "rev/test5-9d58c636cc-9d58c636cc.css",
  "test.css": "test-466b570c16.css",
  "test2.css": "test2-f13f9c6134.css",
  "test3.css": "test3-112b026e30.css",
  "test4.css": "test4-c1beb93e56.css",
  "test5.css": "test5-9d58c636cc.css"
}